Wappalyzer/Wappalyzer.py
Wappalyzer/__init__.py
Wappalyzer/data/technologies.json
python_Wappalyzer-0.3.1.dist-info/LICENSE
python_Wappalyzer-0.3.1.dist-info/METADATA
python_Wappalyzer-0.3.1.dist-info/WHEEL
python_Wappalyzer-0.3.1.dist-info/top_level.txt
python_Wappalyzer-0.3.1.dist-info/RECORD
