Metadata-Version: 2.1
Name: python-Wappalyzer
Version: 0.3.1
Summary: Python implementation of the Wappalyzer web application detection utility
Home-page: https://github.com/chorsley/python-Wappalyzer
Author: Clay McClure, Marcello Salvati (@byt3bl33d3r)
Author-email: clay@daemons.net
License: UNKNOWN
Platform: UNKNOWN
Classifier: Development Status :: 3 - Alpha
Classifier: Intended Audience :: Developers
Classifier: License :: OSI Approved :: GNU General Public License v3 (GPLv3)
Classifier: Programming Language :: Python :: 3
Classifier: Topic :: Internet :: WWW/HTTP
